pelican/plugins/myst_reader/__init__.py
pelican/plugins/myst_reader/_docutils_renderer.py
pelican/plugins/myst_reader/_sphinx_renderer.py
pelican/plugins/myst_reader/exceptions.py
pelican/plugins/myst_reader/myst_reader.py
pelican_myst_reader-1.4.0.dist-info/LICENSE
pelican_myst_reader-1.4.0.dist-info/METADATA
pelican_myst_reader-1.4.0.dist-info/WHEEL
pelican_myst_reader-1.4.0.dist-info/RECORD
