Metadata-Version: 2.1
Name: pelican-myst-reader
Version: 1.4.0
Summary: Pelican plugin for converting MyST's Markdown variant to HTML.
Home-page: https://github.com/ashwinvis/myst-reader
License: AGPL-3.0
Keywords: pelican,plugin,markdown,myst
Author: Ashwin Vishnu
Author-email: dev@fluid.quest
Requires-Python: >=3.10,<4.0
Classifier: Development Status :: 5 - Production/Stable
Classifier: Environment :: Console
Classifier: Framework :: Pelican
Classifier: Framework :: Pelican :: Plugins
Classifier: Intended Audience :: End Users/Desktop
Classifier: License :: OSI Approved :: GNU Affero General Public License v3
Classifier: Operating System :: OS Independent
Classifier: Programming Language :: Python :: 3
Classifier: Programming Language :: Python :: 3.10
Classifier: Programming Language :: Python :: 3.11
Classifier: Programming Language :: Python :: 3.12
Classifier: Topic :: Internet :: WWW/HTTP
Classifier: Topic :: Software Development :: Libraries :: Python Modules
Provides-Extra: markdown
Requires-Dist: beautifulsoup4 (>=4.9.3,<5.0.0)
Requires-Dist: docutils (>=0.19)
Requires-Dist: markdown (>=3.2.2,<4.0.0) ; extra == "markdown"
Requires-Dist: markdown-word-count (>=0.1.0,<0.2.0)
Requires-Dist: myst-parser (>=4.0.0,<5.0.0)
Requires-Dist: pelican (>=4.5,<5.0)
Requires-Dist: pyyaml (>=6.0,<7.0)
Requires-Dist: sphinxcontrib-bibtex (>=2.6.3,<3.0.0)
Project-URL: Documentation, https://docs.getpelican.com
Project-URL: Funding, https://donate.getpelican.com/
Project-URL: Issue Tracker, https://github.com/ashwinvis/myst-reader/issues
Project-URL: Repository, https://github.com/ashwinvis/myst-reader
